{
  "schema_version": 1,
  "run_id": "_fixture",
  "commit": "0000000",
  "branch": "exp/v0",
  "device": "cpu",
  "config": {
    "task": "grid_record_field",
    "seed": 1,
    "generator_version": 1,
    "difficulty": {
      "rows": [
        2,
        6
      ],
      "cols": [
        2,
        6
      ],
      "jitter": 0.0,
      "text": false,
      "background": false
    }
  },
  "metrics": {
    "exact": 0.5,
    "record_acc": 0.75,
    "field_acc": 0.75,
    "baseline_majority_exact": 0.08,
    "baseline_geosort_exact": 0.86
  },
  "curve": [
    {
      "step": 100,
      "train_loss": 2.3,
      "val_exact": 0.12
    },
    {
      "step": 200,
      "train_loss": 1.4,
      "val_exact": 0.5
    }
  ],
  "wall_seconds": 42.0,
  "status": "keep",
  "description": "hand-authored fixture"
}